double_ended_queue/__init__.py
tests/__init__.py
tests/test_foo.py
double_ended_queue-0.1.1.dist-info/LICENSE
double_ended_queue-0.1.1.dist-info/METADATA
double_ended_queue-0.1.1.dist-info/WHEEL
double_ended_queue-0.1.1.dist-info/top_level.txt
double_ended_queue-0.1.1.dist-info/RECORD
