Metadata-Version: 2.1
Name: double-ended-queue
Version: 0.1.1
Summary: An asynchronous Deque Python package based on the asyncio Queue
Home-page: https://github.com/webfucktory/python-double-ended-queue
Author: webfucktory
Author-email: root@webfucktory.com
License: UNKNOWN
Platform: UNKNOWN
Classifier: Development Status :: 5 - Production/Stable
Classifier: Intended Audience :: Developers
Classifier: Natural Language :: English
Classifier: Operating System :: OS Independent
Classifier: Programming Language :: Python :: 3
Classifier: Programming Language :: Python :: 3.8
Classifier: Programming Language :: Python :: 3.9
Classifier: Programming Language :: Python :: 3 :: Only
Requires-Python: >=3.8
License-File: LICENSE
